target_apprise/__init__.py
target_apprise/sinks.py
target_apprise/target.py
target_apprise/tests/__init__.py
target_apprise/tests/test_core.py
target_apprise-0.1.0.dist-info/LICENSE
target_apprise-0.1.0.dist-info/METADATA
target_apprise-0.1.0.dist-info/WHEEL
target_apprise-0.1.0.dist-info/entry_points.txt
target_apprise-0.1.0.dist-info/RECORD
