Metadata-Version: 2.1
Name: target-apprise
Version: 0.1.0
Summary: `target-apprise` is a Singer target for Apprise, built with the Meltano SDK for Singer Targets.
License: Apache 2.0
Keywords: ELT,Apprise
Author: AutoIDM
Requires-Python: >=3.8,<3.12
Classifier: License :: Other/Proprietary License
Classifier: Programming Language :: Python :: 3
Classifier: Programming Language :: Python :: 3.8
Classifier: Programming Language :: Python :: 3.9
Classifier: Programming Language :: Python :: 3.10
Classifier: Programming Language :: Python :: 3.11
Requires-Dist: apprise (==1.5.0)
Requires-Dist: requests (>=2.25.1,<3.0.0)
Requires-Dist: singer-sdk (>=0.41.0,<0.42.0)
